LICENSE
MANIFEST.in
README.md
README.rst
setup.py
denormal/__init__.py
denormal/contrib.py
denormal/fields.py
denormal/models.py
denormal/state.py
denormal/utils.py
denormal/adapters/__init__.py
denormal/adapters/base.py
denormal/adapters/django2p2.py
denormal/adapters/django3p0.py
denormal/adapters/django3p1.py
denormal/adapters/django3p2.py
denormal/adapters/django4p0.py
denormal/management/__init__.py
denormal/management/commands/__init__.py
denormal/management/commands/update_abnorm_fields.py
denormal_tests/__init__.py
denormal_tests/manage.py
denormal_tests/settings.py
denormal_tests/urls.py
denormal_tests/tests/__init__.py
denormal_tests/tests/models.py
denormal_tests/tests/test_adapters.py
denormal_tests/tests/test_commands.py
denormal_tests/tests/test_fields.py
denormal_tests/tests/migrations/0001_initial.py
denormal_tests/tests/migrations/__init__.py
django_denormal.egg-info/PKG-INFO
django_denormal.egg-info/SOURCES.txt
django_denormal.egg-info/dependency_links.txt
django_denormal.egg-info/requires.txt
django_denormal.egg-info/top_level.txt